python_dict_wrapper.py
python_dict_wrapper-1.1.1.dist-info/LICENSE
python_dict_wrapper-1.1.1.dist-info/METADATA
python_dict_wrapper-1.1.1.dist-info/WHEEL
python_dict_wrapper-1.1.1.dist-info/top_level.txt
python_dict_wrapper-1.1.1.dist-info/RECORD
