Metadata-Version: 2.1
Name: python-dict-wrapper
Version: 1.1.1
Summary: A dictionary wrapper
Author-email: Steve Brettschneider <steve@bluehousefamily.com>
License: GNU AFFERO GENERAL PUBLIC LICENSE
Project-URL: Homepage, https://github.com/brettschneider/python_dict_wrapper
Project-URL: Bug Tracker, https://github.com/brettschneider/python_dict_wrapper/issues
Classifier: Programming Language :: Python :: 3
Classifier: License :: OSI Approved :: GNU General Public License v3 or later (GPLv3+)
Classifier: Operating System :: OS Independent
Requires-Python: >=3.8
License-File: LICENSE
